{"frames":{"button_down.png":{"frame":{"x":1,"y":1,"w":227,"h":79},"rotated":false,"trimmed":false,"spriteSourceSize":{"x":0,"y":0,"w":227,"h":79},"sourceSize":{"w":227,"h":79}},"button_normal.png":{"frame":{"x":1,"y":83,"w":227,"h":79},"rotated":false,"trimmed":false,"spriteSourceSize":{"x":0,"y":0,"w":227,"h":79},"sourceSize":{"w":227,"h":79}},"hk.png":{"frame":{"x":231,"y":1,"w":75,"h":100},"rotated":false,"trimmed":false,"spriteSourceSize":{"x":0,"y":0,"w":75,"h":100},"sourceSize":{"w":75,"h":100}},"die_1.png":{"frame":{"x":231,"y":104,"w":49,"h":49},"rotated":false,"trimmed":false,"spriteSourceSize":{"x":0,"y":0,"w":49,"h":49},"sourceSize":{"w":49,"h":49}},"walk_1.png":{"frame":{"x":309,"y":1,"w":49,"h":48},"rotated":false,"trimmed":false,"spriteSourceSize":{"x":0,"y":0,"w":49,"h":48},"sourceSize":{"w":49,"h":48}},"walk_2.png":{"frame":{"x":309,"y":52,"w":49,"h":48},"rotated":false,"trimmed":false,"spriteSourceSize":{"x":0,"y":0,"w":49,"h":48},"sourceSize":{"w":49,"h":48}},"walk_3.png":{"frame":{"x":309,"y":103,"w":49,"h":48},"rotated":false,"trimmed":false,"spriteSourceSize":{"x":0,"y":0,"w":49,"h":48},"sourceSize":{"w":49,"h":48}},"walk_4.png":{"frame":{"x":361,"y":1,"w":49,"h":48},"rotated":false,"trimmed":false,"spriteSourceSize":{"x":0,"y":0,"w":49,"h":48},"sourceSize":{"w":49,"h":48}}},"meta":{"app":"QCEngine","version":"1.0","image":"StickHero","format":"RGBA8888","size":{"w":512,"h":256},"scale":"1"}}
